divyesh_utils/__init__.py
divyesh_utils/db_utils.py
divyesh_utils/err_utils.py
divyesh_utils/user_utils.py
divyesh_utils-1.0.0.dist-info/METADATA
divyesh_utils-1.0.0.dist-info/WHEEL
divyesh_utils-1.0.0.dist-info/top_level.txt
divyesh_utils-1.0.0.dist-info/RECORD
